quark_plugin_devices_dwave/__init__.py
quark_plugin_devices_dwave/simulated_annealer.py
quark_plugin_devices_dwave-0.1.3.dist-info/METADATA
quark_plugin_devices_dwave-0.1.3.dist-info/WHEEL
quark_plugin_devices_dwave-0.1.3.dist-info/licenses/LICENSE
quark_plugin_devices_dwave-0.1.3.dist-info/RECORD
