Metadata-Version: 2.4
Name: QUARK-plugin-devices-dwave
Version: 0.1.3
Summary: Quark plugin providing D-Wave device modules
Project-URL: Homepage, https://github.com/QUARK-framework/QUARK-plugin-devices-dwave
Author-email: Philipp Ross <philipp.ross@bmw.de>, Marvin Erdmann <marvin.erdmann@bmw.de>, Andre Luckow <andre.luckow@bmwgroup.com>, Greshma Shaji <greshma.shaji@bmwgroup.com>, Florian Kiwit <florian.kiwit@bmw.de>, Benjamin Decker <benjamin.decker@bmw.de>
License-Expression: Apache-2.0
License-File: LICENSE
Classifier: Operating System :: OS Independent
Classifier: Programming Language :: Python :: 3
Requires-Python: >=3.12
Requires-Dist: dwave-samplers>=1.4.0
Requires-Dist: quark-framework>=0.1.9
